flixy/__init__.py
flixy/Demo/__init__.py
flixy/Demo/demo.py
flixy/Learn/__init__.py
flixy/Learn/learn.py
flixy/Learn/lessons/Text.py
flixy/Learn/lessons/__init__.py
flixy/Learn/lessons/app.py
flixy/Learn/lessons/button.py
flixy/Learn/lessons/column.py
flixy/Learn/lessons/navigate.py
flixy/Learn/lessons/page.py
flixy/Learn/lessons/row.py
flixy/Learn/lessons/sheet.py
flixy/Learn/lessons/textfield.py
flixy/Learn/lessons/webview.py
flixy/flixy/APP.py
flixy/flixy/PAGE.py
flixy/flixy/__init__.py
flixy/flixy/installer.py
flixy/flixy/update.py
flixy/flixy/Tools/Haptics.py
flixy/flixy/Tools/__init__.py
flixy/flixy/Tools/action.py
flixy/flixy/Tools/convert_rgb_to_hex.py
flixy/flixy/Tools/error_handle.py
flixy/flixy/Tools/expander.py
flixy/flixy/Tools/get_parent.py
flixy/flixy/Tools/sounds.py
flixy/flixy/Tools/subscribers/__init__.py
flixy/flixy/Tools/subscribers/call_on_change.py
flixy/flixy/Tools/subscribers/text_subscribe.py
flixy/flixy/controls/APPBAR.py
flixy/flixy/controls/BUTTON.py
flixy/flixy/controls/COLUMN.py
flixy/flixy/controls/CONTAINER.py
flixy/flixy/controls/NAVIGATOR.py
flixy/flixy/controls/ROW.py
flixy/flixy/controls/SHEET.py
flixy/flixy/controls/SLIDER.py
flixy/flixy/controls/SWITCH.py
flixy/flixy/controls/TEXT.py
flixy/flixy/controls/TEXTFIELD.py
flixy/flixy/controls/TEXTVIEW.py
flixy/flixy/controls/WEBVIEW.py
flixy/flixy/controls/__init__.py
flixy/flixy/controls/audio.py
flixy/flixy/pythonista_ui/VIEW.py
flixy/flixy/pythonista_ui/WKWEBVIEW.py
flixy/flixy/pythonista_ui/__init__.py
flixy/flixy/pythonista_ui/tools/__init__.py
flixy/flixy/pythonista_ui/tools/gestures.py
flixy/flixy/widgets/__init__.py
flixy/flixy/widgets/on_top.py
flixy2app/__init__.py
flixy2app/converter.py
flixy2app/generate.py
flixy2app-0.2.4.dist-info/LICENSE
flixy2app-0.2.4.dist-info/METADATA
flixy2app-0.2.4.dist-info/WHEEL
flixy2app-0.2.4.dist-info/top_level.txt
flixy2app-0.2.4.dist-info/RECORD
