Metadata-Version: 2.1
Name: flixy2app
Version: 0.2.4
Summary: A UI-Builder that helps programmers build the front-end without codding it.
Home-page: https://github.com/SKbarbon/flixy
Author: SKbarbon
Classifier: Programming Language :: Python :: 3
Classifier: Operating System :: MacOS :: MacOS X
Classifier: Operating System :: Microsoft :: Windows
License-File: LICENSE
Requires-Dist: flet
Requires-Dist: requests
Requires-Dist: PyInstaller
